{
    "entries":[
        {
			"dimId":-2,
			"weather":false,
			"haze":false,
			"aurora":false,
			"seaLevel":0,
			"skyHeight":900,
			"cloudHeight":1000
		},
        {
			"dimId":-3,
			"weather":false,
			"haze":false,
			"aurora":false,
			"seaLevel":0,
			"skyHeight":900,
			"cloudHeight":1000
		},
        {
			"dimId":-4,
			"weather":false,
			"haze":false,
			"aurora":false,
			"seaLevel":0,
			"skyHeight":900,
			"cloudHeight":1000
		},
        {
			"dimId":-5,
			"weather":false,
			"haze":false,
			"aurora":false,
			"seaLevel":0,
			"skyHeight":900,
			"cloudHeight":1000
		},
        {
			"dimId":-6,
			"weather":false,
			"haze":false,
			"aurora":false,
			"seaLevel":0,
			"skyHeight":900,
			"cloudHeight":1000
		},
        {
			"dimId":-7,
			"weather":false,
			"haze":false,
			"aurora":false,
			"seaLevel":0,
			"skyHeight":900,
			"cloudHeight":1000
		},
        {
			"dimId":-30,
			"weather":false,
			"haze":false,
			"aurora":false,
			"seaLevel":0,
			"skyHeight":900,
			"cloudHeight":1000
		}
    ]
}